hydroai/__init__.py
hydroai/_nbdev.py
hydroai/core.py
hydroai/data.py
hydroai/model/__init__.py
hydroai/model/data.py
hydroai/model/evaluation.py
hydroai-0.0.1.dist-info/LICENSE
hydroai-0.0.1.dist-info/METADATA
hydroai-0.0.1.dist-info/WHEEL
hydroai-0.0.1.dist-info/entry_points.txt
hydroai-0.0.1.dist-info/top_level.txt
hydroai-0.0.1.dist-info/RECORD
